aws_session_recorder/__init__.py
aws_session_recorder/__main__.py
aws_session_recorder/lib/__init__.py
aws_session_recorder/lib/helpers.py
aws_session_recorder/lib/schema/__init__.py
aws_session_recorder/lib/schema/base.py
aws_session_recorder/lib/schema/functions.py
aws_session_recorder/lib/schema/group.py
aws_session_recorder/lib/schema/identity.py
aws_session_recorder/lib/schema/policy.py
aws_session_recorder/lib/schema/role.py
aws_session_recorder/lib/schema/user.py
aws_session_recorder/lib/session.py
aws_session_recorder/main.py
aws_session_recorder-0.2.2.dist-info/entry_points.txt
aws_session_recorder-0.2.2.dist-info/LICENSE
aws_session_recorder-0.2.2.dist-info/WHEEL
aws_session_recorder-0.2.2.dist-info/METADATA
aws_session_recorder-0.2.2.dist-info/RECORD
